datascraper/__init__.py
datascraper/module1.py
tests/__init__.py
tests/test_module1.py
petroineos_datascraper-1.0.dist-info/LICENSE
petroineos_datascraper-1.0.dist-info/METADATA
petroineos_datascraper-1.0.dist-info/WHEEL
petroineos_datascraper-1.0.dist-info/top_level.txt
petroineos_datascraper-1.0.dist-info/RECORD
