Metadata-Version: 2.1
Name: petroineos_datascraper
Version: 1.0
Summary: Scrapes energy data from UK gov website
Home-page: https://github.com/programmatick/datascraper
Author: Assad Khan
Author-email: assad.beta@gmail.com
Classifier: Programming Language :: Python
Requires-Python: >=3.7
License-File: LICENSE
